python_aisweb/__init__.py
python_aisweb/python_aisweb.py
python_aisweb-1.1.0.dist-info/LICENSE
python_aisweb-1.1.0.dist-info/METADATA
python_aisweb-1.1.0.dist-info/WHEEL
python_aisweb-1.1.0.dist-info/top_level.txt
python_aisweb-1.1.0.dist-info/RECORD
