Metadata-Version: 2.1
Name: python-aisweb
Version: 1.1.0
Summary: API Wrapper for brazilian AIS services.
Home-page: https://github.com/carlosdamazio/python-aisweb
Author: Carlos Damázio
Author-email: kaduardobsb95@gmail.com
License: MIT
Keywords: dev,api,aisweb,aeronautics
Platform: UNKNOWN
Classifier: Intended Audience :: Developers
Classifier: License :: OSI Approved :: MIT License
Classifier: Natural Language :: English
Classifier: Programming Language :: Python :: 2
Classifier: Programming Language :: Python :: 3
Requires-Dist: certifi (==2018.1.18)
Requires-Dist: chardet (==3.0.4)
Requires-Dist: idna (==2.6)
Requires-Dist: urllib3 (==1.24.2)
Requires-Dist: requests (==2.20.0)
Requires-Dist: xmltodict (==0.11.0)
